kotordiff/__init__.py
kotordiff/__main__.py
kotordiff/app.py
kotordiff/cli.py
kotordiff/cli_utils.py
kotordiff/differ.py
kotordiff/formatters.py
kotordiff/gui.py
kotordiff/logger.py
kotor_diff-1.0.1.dist-info/LICENSE
kotor_diff-1.0.1.dist-info/METADATA
kotor_diff-1.0.1.dist-info/WHEEL
kotor_diff-1.0.1.dist-info/entry_points.txt
kotor_diff-1.0.1.dist-info/top_level.txt
kotor_diff-1.0.1.dist-info/RECORD
